{
  "_class": "text",
  "attributedString": {
    "_class": "attributedString",
    "attributes": [
      {
        "_class": "stringAttribute",
        "attributes": {
          "MSAttributedStringColorAttribute": {
            "_class": "color",
            "alpha": 1,
            "blue": 0.1568627450980392,
            "green": 0.1568627450980392,
            "red": 0.1568627450980392
          },
          "MSAttributedStringFontAttribute": {
            "_class": "fontDescriptor",
            "attributes": {
              "name": "HKGrotesk-Regular",
              "size": 22
            }
          },
          "kerning": 0,
          "paragraphStyle": {
            "_class": "paragraphStyle",
            "alignment": 0,
            "baseWritingDirection": 0,
            "headerLevel": 1,
            "maximumLineHeight": 22,
            "minimumLineHeight": 22
          },
          "textStyleVerticalAlignmentKey": 0
        },
        "length": 18,
        "location": 0
      }
    ],
    "string": "projetos paralelos"
  },
  "automaticallyDrawOnUnderlyingPath": false,
  "booleanOperation": -1,
  "clippingMaskMode": 0,
  "do_objectID": "08FDBFB7-CDB1-45DC-BD1E-1B43E752F054",
  "dontSynchroniseWithSymbol": false,
  "exportOptions": {
    "_class": "exportOptions",
    "do_objectID": "52548C88-F1C7-41E3-8ECE-A45B49ADAE45",
    "exportFormats": [
    ],
    "includedLayerIds": [
    ],
    "layerOptions": 0,
    "shouldTrim": false
  },
  "frame": {
    "_class": "rect",
    "constrainProportions": false,
    "do_objectID": "795B6731-3DAC-4A72-B0B0-21CD381E30F5",
    "height": 22,
    "width": 684,
    "x": 99,
    "y": 1435
  },
  "glyphBounds": "{{1, 2}, {175, 21}}",
  "hasClippingMask": false,
  "isFixedToViewport": false,
  "isFlippedHorizontal": false,
  "isFlippedVertical": false,
  "isLocked": false,
  "isVisible": true,
  "layerListExpandedType": 0,
  "lineSpacingBehaviour": 2,
  "name": "projetos paralelos",
  "nameIsFixed": false,
  "resizingConstraint": 47,
  "resizingType": 0,
  "rotation": 0,
  "shouldBreakMaskChain": false,
  "style": {
    "_class": "style",
    "do_objectID": "050EF34D-FA36-4F08-84F5-7C0CC4B7BAF4",
    "endMarkerType": 0,
    "miterLimit": 10,
    "startMarkerType": 0,
    "textStyle": {
      "_class": "textStyle",
      "do_objectID": "7EA03B93-3267-4D82-ACDF-EDB5AFE84380",
      "encodedAttributes": {
        "MSAttributedStringColorAttribute": {
          "_class": "color",
          "alpha": 1,
          "blue": 0.1568627450980392,
          "green": 0.1568627450980392,
          "red": 0.1568627450980392
        },
        "MSAttributedStringFontAttribute": {
          "_class": "fontDescriptor",
          "attributes": {
            "name": "HKGrotesk-Regular",
            "size": 22
          }
        },
        "kerning": 0,
        "paragraphStyle": {
          "_class": "paragraphStyle",
          "alignment": 0,
          "baseWritingDirection": 0,
          "headerLevel": 1,
          "maximumLineHeight": 22,
          "minimumLineHeight": 22
        },
        "textStyleVerticalAlignmentKey": 0
      },
      "verticalAlignment": 0
    },
    "windingRule": 1
  },
  "textBehaviour": 1
}