{
  "_class": "shapePath",
  "booleanOperation": -1,
  "clippingMaskMode": 0,
  "do_objectID": "7D3092E3-19BE-4EA1-AC86-96BA26B1106F",
  "edited": true,
  "exportOptions": {
    "_class": "exportOptions",
    "do_objectID": "0BC43F2A-10CE-4F8C-A0E1-5A58BC6E8197",
    "exportFormats": [
    ],
    "includedLayerIds": [
    ],
    "layerOptions": 0,
    "shouldTrim": false
  },
  "frame": {
    "_class": "rect",
    "constrainProportions": false,
    "do_objectID": "732EA5AF-8820-4DEF-B129-7FCDCDAE5B57",
    "height": 2.549999999999997,
    "width": 2.670000000000002,
    "x": 39.31,
    "y": 21.12
  },
  "hasClippingMask": false,
  "isClosed": true,
  "isFixedToViewport": false,
  "isFlippedHorizontal": false,
  "isFlippedVertical": false,
  "isLocked": false,
  "isVisible": true,
  "layerListExpandedType": 0,
  "name": "Path",
  "nameIsFixed": false,
  "pointRadiusBehaviour": 1,
  "points": [
    {
      "_class": "curvePoint",
      "cornerRadius": 0,
      "curveFrom": "{1, 0.69019682352940936}",
      "curveMode": 2,
      "curveTo": "{1, 0.38431294117646897}",
      "hasCurveFrom": true,
      "hasCurveTo": true,
      "point": "{1, 0.54117647058823415}"
    },
    {
      "_class": "curvePoint",
      "cornerRadius": 0,
      "curveFrom": "{0.72846387640449695, 0.9607847058823541}",
      "curveMode": 2,
      "curveTo": "{0.94569342696629333, 0.80392117647058903}",
      "hasCurveFrom": true,
      "hasCurveTo": true,
      "point": "{0.83707865168539253, 0.88235294117647156}"
    },
    {
      "_class": "curvePoint",
      "cornerRadius": 0,
      "curveFrom": "{0.35580460674157444, 1}",
      "curveMode": 2,
      "curveTo": "{0.61048752808989037, 1}",
      "hasCurveFrom": true,
      "hasCurveTo": true,
      "point": "{0.48314606741573235, 1}"
    },
    {
      "_class": "curvePoint",
      "cornerRadius": 0,
      "curveFrom": "{0.048688651685393818, 0.73529358823529856}",
      "curveMode": 2,
      "curveTo": "{0.24344617977528057, 0.94705935294117638}",
      "hasCurveFrom": true,
      "hasCurveTo": true,
      "point": "{0.14606741573033719, 0.84117647058823464}"
    },
    {
      "_class": "curvePoint",
      "cornerRadius": 0,
      "curveFrom": "{0, 0.34117564705882442}",
      "curveMode": 3,
      "curveTo": "{0, 0.62353000000000058}",
      "hasCurveFrom": true,
      "hasCurveTo": true,
      "point": "{0, 0.5058823529411739}"
    },
    {
      "_class": "curvePoint",
      "cornerRadius": 0,
      "curveFrom": "{0.26217280898876577, 0.043136823529409334}",
      "curveMode": 2,
      "curveTo": "{0.052433932584269038, 0.21568670588235433}",
      "hasCurveFrom": true,
      "hasCurveTo": true,
      "point": "{0.1573033707865174, 0.12941176470588184}"
    },
    {
      "_class": "curvePoint",
      "cornerRadius": 0,
      "curveFrom": "{0.68539404494382039, 0}",
      "curveMode": 3,
      "curveTo": "{0.38576707865168525, 0}",
      "hasCurveFrom": true,
      "hasCurveTo": true,
      "point": "{0.52808988764045317, 0}"
    },
    {
      "_class": "curvePoint",
      "cornerRadius": 0,
      "curveFrom": "{0.96067455056179951, 0.2549024705882354}",
      "curveMode": 2,
      "curveTo": "{0.80337039325842707, 0.050979882352941853}",
      "hasCurveFrom": true,
      "hasCurveTo": true,
      "point": "{0.88202247191011329, 0.15294117647058864}"
    }
  ],
  "resizingConstraint": 63,
  "resizingType": 0,
  "rotation": 0,
  "shouldBreakMaskChain": false,
  "style": {
    "_class": "style",
    "borders": [
      {
        "_class": "border",
        "color": {
          "_class": "color",
          "alpha": 1,
          "blue": 0,
          "green": 0,
          "red": 0
        },
        "fillType": 0,
        "isEnabled": true,
        "position": 0,
        "thickness": 0.5
      }
    ],
    "do_objectID": "1CCF3428-C64F-4D8C-96E4-F900DF111063",
    "endMarkerType": 0,
    "fills": [
      {
        "_class": "fill",
        "color": {
          "_class": "color",
          "alpha": 1,
          "blue": 0,
          "green": 0,
          "red": 0
        },
        "fillType": 0,
        "isEnabled": true,
        "noiseIndex": 0,
        "noiseIntensity": 0,
        "patternFillType": 1,
        "patternTileScale": 1
      }
    ],
    "miterLimit": 10,
    "startMarkerType": 0,
    "textStyle": {
      "_class": "textStyle",
      "do_objectID": "796C291F-592E-439E-B3DF-E9A1A32EE718",
      "encodedAttributes": {
        "MSAttributedStringColorAttribute": {
          "_class": "color",
          "alpha": 1,
          "blue": 0,
          "green": 0,
          "red": 0
        },
        "MSAttributedStringFontAttribute": {
          "_class": "fontDescriptor",
          "attributes": {
            "name": "TrumpGothicEast",
            "size": 30
          }
        },
        "kerning": 1,
        "paragraphStyle": {
          "_class": "paragraphStyle",
          "alignment": 2,
          "baseWritingDirection": 0,
          "headerLevel": 1
        },
        "textStyleVerticalAlignmentKey": 0
      },
      "verticalAlignment": 0
    },
    "windingRule": 1
  }
}